{
    "blog1":{
        "slug": "post-1",
        "type": "lifestyle",
        "name": "Understanding the Difference: Static Generated Sites vs. WordPress",
        "sentence": "Post Sentence 1",
        "date": "09/11/2001",
        "author": "Nicki Faircloth",
        "content": {
            "p1": "In the world of web development, creating a website can be achieved through various means. Two popular options are using static site generators and WordPress. Although they may seem similar at first glance, they have distinct differences that cater to different needs. Let's break down both options.",
            "p2": "Lorem ipsum dolor sit amet, consectetur adipiscing elit, sed do eiusmod tempor incididunt ut labore",
            "p3": "Lorem ipsum dolor sit amet, consectetur adipiscing elit, sed do eiusmod tempor incididunt ut laboreLorem ipsum dolor sit amet, consectetur adipiscing elit, sed do eiusmod tempor incididunt ut labore",
            "p4": "",
            "p5": "",
            "p6": ""
        }
    },
    "blog2":{
        "slug": "post-2",
        "type": "Post Type 2",
        "name": "Post Tile 2 ",
        "sentence": "Post Sentence 2",
        "date": "09/11/2001",
        "author": "Nicki Faircloth",
        "content": {
            "p1": "Lorem ipsum dolor sit amet, consectetur adipiscing elit, sed do eiusmod tempor incididunt ut labore et dolore magna aliqua. Ut enim ad minim veniam, quis nostrud exercitation ullamco laboris nisi ut aliquip ex ea commodo consequat. Duis aute irure dolor in reprehenderit in voluptate velit esse cillum dolore eu fugiat nulla pariatur. Excepteur sint occaecat cupidatat non proident, sunt in culpa qui officia deserunt mollit anim id est laborum",
            "p2": "",
            "p3": "",
            "p4": "",
            "p5": "",
            "p6": ""
        }
    },
    "blog3":{
        "slug": "post-3",
        "type": "lifestyle",
        "name": "Post 3",
        "sentence": "Post Sentence 3",
        "date": "09/11/2001",
        "author": "Nicki Faircloth",
        "content": {
            "p1": "",
            "p2": "",
            "p3": "",
            "p4": "",
            "p5": "",
            "p6": ""
        }
    },
    "blog4":{
        "slug": "post-4",
        "type": "lifestyle",
        "name": "Post 4",
        "sentence": "Post Sentence 4",
        "date": "09/11/2001",
        "content": {
            "p1": "",
            "p2": "",
            "p3": "",
            "p4": "",
            "p5": "",
            "p6": ""
        }
    }
}